eng_syl/__init__.py
eng_syl/clean.pkl
eng_syl/clean_onc.pkl
eng_syl/e2i.pkl
eng_syl/e2i_onc.pkl
eng_syl/onceler.py
eng_syl/onceler_best_weights.h5
eng_syl/op_best_weights.h5
eng_syl/op_d2i.pkl
eng_syl/op_e2i.pkl
eng_syl/phonify.py
eng_syl/syllabify.py
eng_syl/syllabler_best_weights.h5
eng_syl-4.0.8.2.dist-info/LICENSE
eng_syl-4.0.8.2.dist-info/METADATA
eng_syl-4.0.8.2.dist-info/WHEEL
eng_syl-4.0.8.2.dist-info/top_level.txt
eng_syl-4.0.8.2.dist-info/RECORD
