Metadata-Version: 2.1
Name: eng-syl
Version: 4.0.8.2
Summary: English word syllabifier and extended syllable analysis tool
Home-page: https://github.com/timo-liu/eng-syl
Author: Timothy-Liu
Author-email: timothys.new.email@gmail.com
License: MIT
Keywords: Syllable,NLP,psycholinguistics
Classifier: Development Status :: 3 - Alpha
Classifier: Intended Audience :: Developers
Classifier: Topic :: Software Development :: Build Tools
Classifier: License :: OSI Approved :: MIT License
Classifier: Programming Language :: Python :: 3.8
License-File: LICENSE
Requires-Dist: tensorflow
Requires-Dist: numpy
